fastcp/Collections.py
fastcp/__init__.py
fastcp/arrays.py
fastcp/bitMan.py
fastcp/dataStructures.py
fastcp/math.py
fastcp/search.py
fastcp/sorting.py
fastcp/strings.py
fastcp/trees.py
tests/__init__.py
fastcp-1.0.6.1.dist-info/LICENSE.txt
fastcp-1.0.6.1.dist-info/METADATA
fastcp-1.0.6.1.dist-info/WHEEL
fastcp-1.0.6.1.dist-info/top_level.txt
fastcp-1.0.6.1.dist-info/RECORD
