Metadata-Version: 2.1
Name: fastcp
Version: 1.0.6.1
Summary: A Python Package for Competitive Programming
Home-page: https://github.com/avinash-doddi/fastcp.git
Author: Avinash Doddi
Author-email: avinashdoddi2001@gmail.com
Project-URL: Bug Tracker, https://github.com/avinash-doddi/fastcp.git
Classifier: Programming Language :: Python :: 3
Classifier: License :: OSI Approved :: MIT License
Classifier: Operating System :: OS Independent
Requires-Python: >=3.6
License-File: LICENSE.txt
